cluster_ss/__init__.py
cluster_ss/plots.py
cluster_ss/sils.py
cluster_ss/utils.py
cluster_ss-0.0.5.dist-info/LICENSE
cluster_ss-0.0.5.dist-info/METADATA
cluster_ss-0.0.5.dist-info/WHEEL
cluster_ss-0.0.5.dist-info/RECORD
